noselisting.py
setup.py
noselisting.egg-info/PKG-INFO
noselisting.egg-info/SOURCES.txt
noselisting.egg-info/dependency_links.txt
noselisting.egg-info/entry_points.txt
noselisting.egg-info/requires.txt
noselisting.egg-info/top_level.txt
noselisting.egg-info/zip-safe
